Workbook
Name Slicer_Category: #N/A
Name Slicer_Region1: #N/A

Sheet Sales Data
A1: Date | B1: Region | C1: City | D1: Customer Type | E1: Channel | F1: Product | G1: Category | H1: Unit Price | I1: Quantity | J1: Sales Rep | K1: Cost Price
A2: 45676 | B2: West | C2: Port Harcourt | D2: Retail | E2: Online | F2: Office Chair Pro | G2: Furniture | H2: 85000 | I2: 1 | J2: Chidinma | K2: 68000
A3: 45776 | B3: East | C3: Lagos | D3: Retail | E3: Store | F3: Blender B10 | G3: Home Appliances | H3: 30000 | I3: 8 | J3: Chidinma | K3: 24000
A4: 45715 | B4: East | C4: Port Harcourt | D4: Corporate | E4: Online | F4: Office Chair Pro | G4: Furniture | H4: 85000 | I4: 2 | J4: David | K4: 68000
A5: 45772 | B5: South | C5: Kano | D5: Retail | E5: Online | F5: Microwave M20 | G5: Home Appliances | H5: 60000 | I5: 2 | J5: Musa | K5: 48000
A6: 45774 | B6: North | C6: Kano | D6: Corporate | E6: Online | F6: Desktop PC D21 | G6: Electronics | H6: 300000 | I6: 2 | J6: Chidinma | K6: 240000
A7: 45724 | B7: South | C7: Abuja | D7: Retail | E7: Online | F7: Air Conditioner X2 | G7: Home Appliances | H7: 180000 | I7: 10 | J7: Chidinma | K7: 144000
A8: 45725 | B8: South | C8: Abuja | D8: Corporate | E8: Online | F8: Sofa Classic | G8: Furniture | H8: 320000 | I8: 4 | J8: Musa | K8: 256000
A9: 45694 | B9: South | C9: Kano | D9: Retail | E9: Online | F9: Sofa Classic | G9: Furniture | H9: 320000 | I9: 1 | J9: Peter | K9: 256000
A10: 45740 | B10: East | C10: Lagos | D10: Retail | E10: Store | F10: Sofa Classic | G10: Furniture | H10: 320000 | I10: 9 | J10: Musa | K10: 256000
A11: 45742 | B11: South | C11: Lagos | D11: Retail | E11: Online | F11: Sofa Classic | G11: Furniture | H11: 320000 | I11: 3 | J11: Musa | K11: 256000
A12: 45681 | B12: South | C12: Port Harcourt | D12: Retail | E12: Online | F12: Printer P50 | G12: Electronics | H12: 150000 | I12: 4 | J12: Peter | K12: 120000
A13: 45677 | B13: West | C13: Kano | D13: Corporate | E13: Online | F13: Sofa Classic | G13: Furniture | H13: 320000 | I13: 7 | J13: Peter | K13: 256000
... A2099: 45693 | B2099: South | C2099: Port Harcourt | D2099: Retail | E2099: Online | F2099: Sofa Classic | G2099: Furniture | H2099: 320000 | I2099: 4 | J2099: David | K2099: 256000

Sheet Working Sheet
A1: Customer | B1: Date | C1: Month | D1: Region | E1: City | F1: Customer Type | G1: Channel | H1: Product | I1: Category | J1: Unit Price | K1: Quantity | L1: Sales Rep | M1: Cost Price | N1: Revenue | O1: COGS | P1: Profit
A2: ="ID_"& RANDBETWEEN(1,2098) -> ID_466 | B2: 45676 | C2: =TEXT('Working Sheet'!$B2,"mmm") -> Jan | D2: West | E2: Port Harcourt | F2: Retail | G2: Online | H2: Office Chair Pro | I2: Furniture | J2: 85000 | K2: 1 | L2: Chidinma | M2: =J2-J2*0.2 -> 68000 | N2: ='Working Sheet'!$J2*'Working Sheet'!$K2 -> 85000 | O2: ='Working Sheet'!$M2*'Working Sheet'!$K2 -> 68000 | P2: ='Working Sheet'!$N2-'Working Sheet'!$O2 -> 17000
A3: ="ID_"& RANDBETWEEN(1,2098) -> ID_199 | B3: 45776 | C3: =TEXT('Working Sheet'!$B3,"mmm") -> Apr | D3: East | E3: Lagos | F3: Retail | G3: Store | H3: Blender B10 | I3: Home Appliances | J3: 30000 | K3: 8 | L3: Chidinma | M3: =J3-J3*0.2 -> 24000 | N3: ='Working Sheet'!$J3*'Working Sheet'!$K3 -> 240000 | O3: ='Working Sheet'!$M3*'Working Sheet'!$K3 -> 192000 | P3: ='Working Sheet'!$N3-'Working Sheet'!$O3 -> 48000
A4: ="ID_"& RANDBETWEEN(1,2098) -> ID_1802 | B4: 45715 | C4: =TEXT('Working Sheet'!$B4,"mmm") -> Feb | D4: East | E4: Port Harcourt | F4: Corporate | G4: Online | H4: Office Chair Pro | I4: Furniture | J4: 85000 | K4: 2 | L4: David | M4: =J4-J4*0.2 -> 68000 | N4: ='Working Sheet'!$J4*'Working Sheet'!$K4 -> 170000 | O4: ='Working Sheet'!$M4*'Working Sheet'!$K4 -> 136000 | P4: ='Working Sheet'!$N4-'Working Sheet'!$O4 -> 34000
A5: ="ID_"& RANDBETWEEN(1,2098) -> ID_881 | B5: 45772 | C5: =TEXT('Working Sheet'!$B5,"mmm") -> Apr | D5: South | E5: Kano | F5: Retail | G5: Online | H5: Microwave M20 | I5: Home Appliances | J5: 60000 | K5: 2 | L5: Musa | M5: =J5-J5*0.2 -> 48000 | N5: ='Working Sheet'!$J5*'Working Sheet'!$K5 -> 120000 | O5: ='Working Sheet'!$M5*'Working Sheet'!$K5 -> 96000 | P5: ='Working Sheet'!$N5-'Working Sheet'!$O5 -> 24000
A6: ="ID_"& RANDBETWEEN(1,2098) -> ID_27 | B6: 45774 | C6: =TEXT('Working Sheet'!$B6,"mmm") -> Apr | D6: North | E6: Kano | F6: Corporate | G6: Online | H6: Desktop PC D21 | I6: Electronics | J6: 300000 | K6: 2 | L6: Chidinma | M6: =J6-J6*0.2 -> 240000 | N6: ='Working Sheet'!$J6*'Working Sheet'!$K6 -> 600000 | O6: ='Working Sheet'!$M6*'Working Sheet'!$K6 -> 480000 | P6: ='Working Sheet'!$N6-'Working Sheet'!$O6 -> 120000
A7: ="ID_"& RANDBETWEEN(1,2098) -> ID_792 | B7: 45724 | C7: =TEXT('Working Sheet'!$B7,"mmm") -> Mar | D7: South | E7: Abuja | F7: Retail | G7: Online | H7: Air Conditioner X2 | I7: Home Appliances | J7: 180000 | K7: 10 | L7: Chidinma | M7: =J7-J7*0.2 -> 144000 | N7: ='Working Sheet'!$J7*'Working Sheet'!$K7 -> 1800000 | O7: ='Working Sheet'!$M7*'Working Sheet'!$K7 -> 1440000 | P7: ='Working Sheet'!$N7-'Working Sheet'!$O7 -> 360000
A8: ="ID_"& RANDBETWEEN(1,2098) -> ID_1103 | B8: 45725 | C8: =TEXT('Working Sheet'!$B8,"mmm") -> Mar | D8: South | E8: Abuja | F8: Corporate | G8: Online | H8: Sofa Classic | I8: Furniture | J8: 320000 | K8: 4 | L8: Musa | M8: =J8-J8*0.2 -> 256000 | N8: ='Working Sheet'!$J8*'Working Sheet'!$K8 -> 1280000 | O8: ='Working Sheet'!$M8*'Working Sheet'!$K8 -> 1024000 | P8: ='Working Sheet'!$N8-'Working Sheet'!$O8 -> 256000
A9: ="ID_"& RANDBETWEEN(1,2098) -> ID_847 | B9: 45694 | C9: =TEXT('Working Sheet'!$B9,"mmm") -> Feb | D9: South | E9: Kano | F9: Retail | G9: Online | H9: Sofa Classic | I9: Furniture | J9: 320000 | K9: 1 | L9: Peter | M9: =J9-J9*0.2 -> 256000 | N9: ='Working Sheet'!$J9*'Working Sheet'!$K9 -> 320000 | O9: ='Working Sheet'!$M9*'Working Sheet'!$K9 -> 256000 | P9: ='Working Sheet'!$N9-'Working Sheet'!$O9 -> 64000
A10: ="ID_"& RANDBETWEEN(1,2098) -> ID_84 | B10: 45740 | C10: =TEXT('Working Sheet'!$B10,"mmm") -> Mar | D10: East | E10: Lagos | F10: Retail | G10: Store | H10: Sofa Classic | I10: Furniture | J10: 320000 | K10: 9 | L10: Musa | M10: =J10-J10*0.2 -> 256000 | N10: ='Working Sheet'!$J10*'Working Sheet'!$K10 -> 2880000 | O10: ='Working Sheet'!$M10*'Working Sheet'!$K10 -> 2304000 | P10: ='Working Sheet'!$N10-'Working Sheet'!$O10 -> 576000
A11: ="ID_"& RANDBETWEEN(1,2098) -> ID_738 | B11: 45742 | C11: =TEXT('Working Sheet'!$B11,"mmm") -> Mar | D11: South | E11: Lagos | F11: Retail | G11: Online | H11: Sofa Classic | I11: Furniture | J11: 320000 | K11: 3 | L11: Musa | M11: =J11-J11*0.2 -> 256000 | N11: ='Working Sheet'!$J11*'Working Sheet'!$K11 -> 960000 | O11: ='Working Sheet'!$M11*'Working Sheet'!$K11 -> 768000 | P11: ='Working Sheet'!$N11-'Working Sheet'!$O11 -> 192000
A12: ="ID_"& RANDBETWEEN(1,2098) -> ID_1036 | B12: 45681 | C12: =TEXT('Working Sheet'!$B12,"mmm") -> Jan | D12: South | E12: Port Harcourt | F12: Retail | G12: Online | H12: Printer P50 | I12: Electronics | J12: 150000 | K12: 4 | L12: Peter | M12: =J12-J12*0.2 -> 120000 | N12: ='Working Sheet'!$J12*'Working Sheet'!$K12 -> 600000 | O12: ='Working Sheet'!$M12*'Working Sheet'!$K12 -> 480000 | P12: ='Working Sheet'!$N12-'Working Sheet'!$O12 -> 120000
A13: ="ID_"& RANDBETWEEN(1,2098) -> ID_2020 | B13: 45677 | C13: =TEXT('Working Sheet'!$B13,"mmm") -> Jan | D13: West | E13: Kano | F13: Corporate | G13: Online | H13: Sofa Classic | I13: Furniture | J13: 320000 | K13: 7 | L13: Peter | M13: =J13-J13*0.2 -> 256000 | N13: ='Working Sheet'!$J13*'Working Sheet'!$K13 -> 2240000 | O13: ='Working Sheet'!$M13*'Working Sheet'!$K13 -> 1792000 | P13: ='Working Sheet'!$N13-'Working Sheet'!$O13 -> 448000
... A2099: ="ID_"& RANDBETWEEN(1,2098) -> ID_165 | B2099: 45693 | C2099: =TEXT('Working Sheet'!$B2099,"mmm") -> Feb | D2099: South | E2099: Port Harcourt | F2099: Retail | G2099: Online | H2099: Sofa Classic | I2099: Furniture | J2099: 320000 | K2099: 4 | L2099: David | M2099: =J2099-J2099*0.2 -> 256000 | N2099: ='Working Sheet'!$J2099*'Working Sheet'!$K2099 -> 1280000 | O2099: ='Working Sheet'!$M2099*'Working Sheet'!$K2099 -> 1024000 | P2099: ='Working Sheet'!$N2099-'Working Sheet'!$O2099 -> 256000
A2100: Total | N2100: =SUBTOTAL(109,Table3[Revenue]) -> 2328370000 | P2100: =SUBTOTAL(109,Table3[Profit]) -> 465674000

Sheet Pivot Table & Chart
A1: Row Labels | B1: Sum of Profit
A2: Laptop A13 | B2: 105336000 | L2: Row Labels | M2: Sum of COGS
A3: Sofa Classic | B3: 69248000 | L3: Abuja | M3: 423312000
A4: Desktop PC D21 | B4: 68640000 | L4: Kano | M4: 486788000
A5: Smartphone Z10 | B5: 51950000 | L5: Lagos | M5: 493812000
A6: Refrigerator R55 | B6: 48312000 | L6: Port Harcourt | M6: 458784000
A7: Air Conditioner X2 | B7: 44964000
A8: Printer P50 | B8: 38850000
A9: Office Chair Pro | B9: 18088000
A10: Microwave M20 | B10: 13416000
A11: Blender B10 | B11: 6870000
A15: Row Labels | B15: Sum of Revenue
A16: Peter | B16: 434805000 | L16: Row Labels | M16: Sum of Revenue
A17: Musa | B17: 397665000 | L17: Jan | M17: 547065000
A18: David | B18: 378660000 | L18: Feb | M18: 552405000
A19: Aisha | B19: 378035000 | L19: Mar | M19: 633440000
A20: Chidinma | B20: 371370000 | L20: Apr | M20: 582155000
A21: Grace | B21: 367835000 | L21: May | M21: 13305000
A27: Sum of Revenue | D27: Sum of COGS | G27: Sum of Profit | J27: Count of Customer | M27: Sum of Quantity
A28: 2328370000 | B28: ="$"&TEXT(GETPIVOTDATA("Revenue",$A$27)/1000000000,"0.00")&"B" -> $2.33B | D28: 1862696000 | E28: ="$"&TEXT(GETPIVOTDATA("COGS",$D$27)/1000000000,"0.00")&"B" -> $1.86B | G28: 465674000 | H28: ="$"&TEXT(GETPIVOTDATA("Profit",$G$27)/1000000,"0.00")&"M" -> $465.67M | J28: 2098 | K28: =GETPIVOTDATA("Customer",$J$27) -> 2098 | M28: 11488 | N28: =GETPIVOTDATA("Quantity",$M$27) -> 11488

Sheet Dashboard

Sheet Key Insights & Findings
A1: Executive Summary
A2: The sales performance analysis reveals strong profitability from key products and sales representatives, alongside significant cost concentration and a sharp decline in monthly revenue. Laptop A13 was the most profitable product, contributing 22.6% of total profit, while Peter was the top-performing sales representative, generating $434.8M in revenue. Lagos and Kano jointly accounted for 52% of total COGS, highlighting opportunities for cost optimization. Revenue peaked at $633.4M in March before falling to $13.3M in May, representing a 97.9% decline.
A3: To improve overall performance, the business should prioritize high-profit products, leverage successful sales practices across the team, investigate cost drivers in Lagos and Kano, and identify the causes of the sharp revenue decline to develop strategies for stabilizing future revenue.
A6: Key Insights & Findings
A7: Laptop A13 contributed 22.6% of total profit making it the most profitable product, while Blender contributed the lowest share 1.5% of overall profit
A8: Peter was the highest-performing sales representative, generating $434.8 million in revenue and contributing 18.6% of the company's total revenue of $2.3 billion
A9: Lagos and Kano each accounted for 26% of total COGS, jointly representing 52% of the company's Cost of Goods Sold making them the largest cost-contributing cities
A10: Revenue peaked in March at $633.4 million before declining to $13.3 million in May, representing a 97.9% decline from the March peak.This indicates a significant deterioration in monthly revenue performance
A13: Recommendations
A14: Analyze the factors driving Laptop A13’s strong profitability and prioritize its availability, marketing, and sales efforts. At the same time, review Blender’s pricing, sales volume, and cost structure to identify opportunities to improve its profitability or determine whether resources should be redirected to higher-performing products
A15: Identify and replicate the strategies, customer segments, and sales practices contributing to Peter’s strong performance across the wider sales team. Lower-performing representatives should also be assessed to identify specific performance gaps and opportunities for targeted support
A16: Investigate the key drivers of COGS in Lagos and Kano, including procurement, logistics, and operating costs, and identify opportunities to reduce costs without negatively affecting sales or customer service
... A21: The findings and recommendations presented are based on the overall dataset with no filters applied. Dashboard filters can be used to explore performance across specific regions, products, categories, and other segments.
